MANIFEST.in
README.md
bumpversion.py
fastentrypoints.py
setup.py
tst.py
daemonctl.egg-info/PKG-INFO
daemonctl.egg-info/SOURCES.txt
daemonctl.egg-info/dependency_links.txt
daemonctl.egg-info/entry_points.txt
daemonctl.egg-info/top_level.txt
src/__init__.py
src/api.py
src/daemon.py
src/daemonconfig.py
src/daemonctl.complete
src/daemonctl.conf
src/daemonctl.init
src/daemonlog.py
src/dts.py
src/fulltb.py
src/locks.py
src/logwriter.py
src/main.py
src/modules.py
src/parsetrace.py
src/piptool.py
src/runasdaemon.py
test/testconfig.py