Metadata-Version: 2.1
Name: daemonctl
Version: 1.3.25
Summary: UNKNOWN
Home-page: https://github.com/SVT/daemonctl
Author: Andreas Åkerlund
Author-email: andreas.akerlund@svt.se
License: SVT internal
Keywords: Python example package
Platform: UNKNOWN
Classifier: Operating System :: POSIX :: Linux
Classifier: Programming Language :: Python :: 2.6
